DeepPhysX.Torch-22.12-py3.10-nspkg.pth
DeepPhysX/Torch/__init__.py
DeepPhysX/Torch/EncoderDecoder/EncoderDecoder.py
DeepPhysX/Torch/EncoderDecoder/__init__.py
DeepPhysX/Torch/FC/FC.py
DeepPhysX/Torch/FC/FCConfig.py
DeepPhysX/Torch/FC/__init__.py
DeepPhysX/Torch/Network/TorchNetwork.py
DeepPhysX/Torch/Network/TorchNetworkConfig.py
DeepPhysX/Torch/Network/TorchOptimization.py
DeepPhysX/Torch/Network/TorchTransformation.py
DeepPhysX/Torch/Network/__init__.py
DeepPhysX/Torch/UNet/UNet.py
DeepPhysX/Torch/UNet/UNetConfig.py
DeepPhysX/Torch/UNet/UnetTransformation.py
DeepPhysX/Torch/UNet/__init__.py
DeepPhysX/Torch/UNet/utils.py
DeepPhysX/examples/Torch/tutorial/FC.py
DeepPhysX/examples/Torch/tutorial/UNet.py
DeepPhysX/examples/Torch/tutorial/__init__.py
DeepPhysX.Torch-22.12.dist-info/LICENSE
DeepPhysX.Torch-22.12.dist-info/METADATA
DeepPhysX.Torch-22.12.dist-info/WHEEL
DeepPhysX.Torch-22.12.dist-info/namespace_packages.txt
DeepPhysX.Torch-22.12.dist-info/top_level.txt
DeepPhysX.Torch-22.12.dist-info/RECORD
