Metadata-Version: 2.1
Name: DeepPhysX.Torch
Version: 22.12
Summary: A PyTorch compatibility layer for DeepPhysX framework.
Home-page: https://github.com/mimesis-inria/DeepPhysX.Torch
Author: Mimesis
Author-email: robin.enjalbert@inria.fr
License-File: LICENSE
Requires-Dist: DeepPhysX (>=22.12)
Requires-Dist: torch (>=1.13.0)
